Workbook

Sheet Comece aqui
B2: Conta Doce · o preço do seu doce em 15 minutos
B4: Células em creme
B5: são as que você preenche. As verdes são calculadas sozinhas. Não apague fórmulas.
B7: Passo 1 · Custos do mês (5 min)
B8: quanto você quer ganhar por mês, quantas horas trabalha na confeitaria e os gastos fixos (gás, luz, internet, DAS).
B10: Passo 2 · Insumos (5 min)
B11: escreva o preço que você pagou só nos ingredientes do seu doce mais vendido. A lista já traz tamanhos comuns de embalagem: confira se o seu é igual.
B13: Passo 3 · Ficha 1 (5 min)
B14: escolha os ingredientes na lista, diga quanto usa, quantas unidades rende e quanto tempo leva. Pronto: aparece o custo real, o preço mínimo e o preço sugerido.
B16: Tabela WhatsApp
B17: junta os preços de todas as fichas em linhas prontas para copiar e mandar para clientes.
B19: Exemplo
... B23: a planilha calcula a partir dos números que você coloca. Ela não sabe o preço da sua região nem garante vendas. Revise os preços dos insumos quando fizer compras.

Sheet Custos do mês
A1: Custos do mês
A3: Quanto você quer ganhar por mês pelo seu trabalho | B3: 2000 | C3: seu pró-labore: o salário que você se paga
A4: Horas por mês trabalhando na confeitaria | B4: 120 | C4: conte produção, compras, embalagem e atendimento
A5: Valor da sua hora | B5: =IFERROR(B3/B4,0)
A6: Gastos fixos por mês
A7: Gás (parte da confeitaria) | B7: 0
A8: Energia (parte da confeitaria) | B8: 0
A9: Água (parte da confeitaria) | B9: 0
A10: Internet e celular (parte do negócio) | B10: 0
A11: DAS do MEI ou impostos | B11: 0 | C11: confira o valor do seu boleto
A12: Utensílios, manutenção e reposição | B12: 0
A13: Outros gastos fixos | B13: 0
A14: Total de gastos fixos | B14: =SUM(B7:B13)
A15: Gasto fixo por hora trabalhada | B15: =IFERROR(B14/B4,0)
A16: Taxas e margem
A17: Taxa da maquininha ou do link de pagamento | B17: 0.04 | C17: exemplo de 4%: troque pela taxa do seu contrato
A18: Taxa do aplicativo de delivery (se usar) | B18: 0 | C18: confira no seu contrato; deixe 0% se não usa
A19: Margem de lucro desejada | B19: 0.3 | C19: quanto sobra para o negócio além do seu pró-labore

Sheet Insumos
A1: Insumos e embalagens
A2: Preencha o preço só do que você usa. Tamanhos de embalagem são comuns no mercado: confira o seu.
A4: Insumo | B4: Unidade | C4: Qtd na embalagem | D4: Preço pago | E4: Custo por unidade
A5: Leite condensado | B5: g | C5: 395 | E5: =IF(AND(C5>0,D5>0),D5/C5,"")
A6: Creme de leite | B6: g | C6: 200 | E6: =IF(AND(C6>0,D6>0),D6/C6,"")
A7: Leite integral | B7: ml | C7: 1000 | E7: =IF(AND(C7>0,D7>0),D7/C7,"")
A8: Leite em pó | B8: g | C8: 200 | E8: =IF(AND(C8>0,D8>0),D8/C8,"")
A9: Manteiga sem sal | B9: g | C9: 200 | E9: =IF(AND(C9>0,D9>0),D9/C9,"")
A10: Margarina | B10: g | C10: 500 | E10: =IF(AND(C10>0,D10>0),D10/C10,"")
A11: Açúcar refinado | B11: g | C11: 1000 | E11: =IF(AND(C11>0,D11>0),D11/C11,"")
A12: Açúcar de confeiteiro | B12: g | C12: 500 | E12: =IF(AND(C12>0,D12>0),D12/C12,"")
A13: Farinha de trigo | B13: g | C13: 1000 | E13: =IF(AND(C13>0,D13>0),D13/C13,"")
A14: Fermento químico | B14: g | C14: 100 | E14: =IF(AND(C14>0,D14>0),D14/C14,"")
A15: Amido de milho | B15: g | C15: 500 | E15: =IF(AND(C15>0,D15>0),D15/C15,"")
A16: Ovos | B16: un | C16: 12 | E16: =IF(AND(C16>0,D16>0),D16/C16,"")
... A56: Sacola | B56: un | C56: 1 | E56: =IF(AND(C56>0,D56>0),D56/C56,"")
E57: =IF(AND(C57>0,D57>0),D57/C57,"")
E58: =IF(AND(C58>0,D58>0),D58/C58,"")
E59: =IF(AND(C59>0,D59>0),D59/C59,"")
E60: =IF(AND(C60>0,D60>0),D60/C60,"")
E61: =IF(AND(C61>0,D61>0),D61/C61,"")
E62: =IF(AND(C62>0,D62>0),D62/C62,"")
E63: =IF(AND(C63>0,D63>0),D63/C63,"")
E64: =IF(AND(C64>0,D64>0),D64/C64,"")
E65: =IF(AND(C65>0,D65>0),D65/C65,"")
E66: =IF(AND(C66>0,D66>0),D66/C66,"")
E67: =IF(AND(C67>0,D67>0),D67/C67,"")
E68: =IF(AND(C68>0,D68>0),D68/C68,"")
... E104: =IF(AND(C104>0,D104>0),D104/C104,"")

Sheet Ficha 1
A1: Ficha 1 · ficha de preço
A2: Produto
A3: Rendimento da receita (unidades)
A4: Tempo para fazer a receita inteira (min)
A5: Embalagem por unidade vendida | E5: forminha, caixa, pote, etiqueta: some o que vai em cada unidade
A7: Ingrediente | B7: Qtd usada | C7: Unidade | D7: Custo
C8: =IF(A8="","",IFERROR(INDEX(Insumos!$B$5:$B$104,MATCH(A8,Insumos!$A$5:$A$104,0)),"")) | D8: =IF(OR(A8="",B8=""),"",IFERROR(B8*INDEX(Insumos!$E$5:$E$104,MATCH(A8,Insumos!$A$5:$A$104,0)),"preencha o preço"))
C9: =IF(A9="","",IFERROR(INDEX(Insumos!$B$5:$B$104,MATCH(A9,Insumos!$A$5:$A$104,0)),"")) | D9: =IF(OR(A9="",B9=""),"",IFERROR(B9*INDEX(Insumos!$E$5:$E$104,MATCH(A9,Insumos!$A$5:$A$104,0)),"preencha o preço"))
C10: =IF(A10="","",IFERROR(INDEX(Insumos!$B$5:$B$104,MATCH(A10,Insumos!$A$5:$A$104,0)),"")) | D10: =IF(OR(A10="",B10=""),"",IFERROR(B10*INDEX(Insumos!$E$5:$E$104,MATCH(A10,Insumos!$A$5:$A$104,0)),"preencha o preço"))
C11: =IF(A11="","",IFERROR(INDEX(Insumos!$B$5:$B$104,MATCH(A11,Insumos!$A$5:$A$104,0)),"")) | D11: =IF(OR(A11="",B11=""),"",IFERROR(B11*INDEX(Insumos!$E$5:$E$104,MATCH(A11,Insumos!$A$5:$A$104,0)),"preencha o preço"))
C12: =IF(A12="","",IFERROR(INDEX(Insumos!$B$5:$B$104,MATCH(A12,Insumos!$A$5:$A$104,0)),"")) | D12: =IF(OR(A12="",B12=""),"",IFERROR(B12*INDEX(Insumos!$E$5:$E$104,MATCH(A12,Insumos!$A$5:$A$104,0)),"preencha o preço"))
C13: =IF(A13="","",IFERROR(INDEX(Insumos!$B$5:$B$104,MATCH(A13,Insumos!$A$5:$A$104,0)),"")) | D13: =IF(OR(A13="",B13=""),"",IFERROR(B13*INDEX(Insumos!$E$5:$E$104,MATCH(A13,Insumos!$A$5:$A$104,0)),"preencha o preço"))
C14: =IF(A14="","",IFERROR(INDEX(Insumos!$B$5:$B$104,MATCH(A14,Insumos!$A$5:$A$104,0)),"")) | D14: =IF(OR(A14="",B14=""),"",IFERROR(B14*INDEX(Insumos!$E$5:$E$104,MATCH(A14,Insumos!$A$5:$A$104,0)),"preencha o preço"))
C15: =IF(A15="","",IFERROR(INDEX(Insumos!$B$5:$B$104,MATCH(A15,Insumos!$A$5:$A$104,0)),"")) | D15: =IF(OR(A15="",B15=""),"",IFERROR(B15*INDEX(Insumos!$E$5:$E$104,MATCH(A15,Insumos!$A$5:$A$104,0)),"preencha o preço"))
C16: =IF(A16="","",IFERROR(INDEX(Insumos!$B$5:$B$104,MATCH(A16,Insumos!$A$5:$A$104,0)),"")) | D16: =IF(OR(A16="",B16=""),"",IFERROR(B16*INDEX(Insumos!$E$5:$E$104,MATCH(A16,Insumos!$A$5:$A$104,0)),"preencha o preço"))
C17: =IF(A17="","",IFERROR(INDEX(Insumos!$B$5:$B$104,MATCH(A17,Insumos!$A$5:$A$104,0)),"")) | D17: =IF(OR(A17="",B17=""),"",IFERROR(B17*INDEX(Insumos!$E$5:$E$104,MATCH(A17,Insumos!$A$5:$A$104,0)),"preencha o preço"))
C18: =IF(A18="","",IFERROR(INDEX(Insumos!$B$5:$B$104,MATCH(A18,Insumos!$A$5:$A$104,0)),"")) | D18: =IF(OR(A18="",B18=""),"",IFERROR(B18*INDEX(Insumos!$E$5:$E$104,MATCH(A18,Insumos!$A$5:$A$104,0)),"preencha o preço"))
C19: =IF(A19="","",IFERROR(INDEX(Insumos!$B$5:$B$104,MATCH(A19,Insumos!$A$5:$A$104,0)),"")) | D19: =IF(OR(A19="",B19=""),"",IFERROR(B19*INDEX(Insumos!$E$5:$E$104,MATCH(A19,Insumos!$A$5:$A$104,0)),"preencha o preço"))
... C22: =IF(A22="","",IFERROR(INDEX(Insumos!$B$5:$B$104,MATCH(A22,Insumos!$A$5:$A$104,0)),"")) | D22: =IF(OR(A22="",B22=""),"",IFERROR(B22*INDEX(Insumos!$E$5:$E$104,MATCH(A22,Insumos!$A$5:$A$104,0)),"preencha o preço"))
A23: Ingredientes da receita | D23: =SUM(D8:D22)
A25: Ingredientes por unidade | D25: =IFERROR(D23/B3,0)
A26: Embalagem por unidade | D26: =N(B5)
A27: Seu trabalho por unidade | D27: =IFERROR(B4/60*'Custos do mês'!B5/B3,0)
A28: Gastos fixos por unidade | D28: =IFERROR(B4/60*'Custos do mês'!B15/B3,0)
A29: CUSTO REAL POR UNIDADE | D29: =SUM(D25:D28)
A31: Preço mínimo (sem lucro, já com a taxa) | D31: =IFERROR(ROUNDUP(D29/(1-'Custos do mês'!B17)*2,0)/2,0) | E31: abaixo disso você paga para trabalhar
A32: PREÇO SUGERIDO (encomenda) | D32: =IFERROR(ROUNDUP(D29/(1-'Custos do mês'!B17-'Custos do mês'!B19)*2,0)/2,0) | E32: arredondado para cima em R$ 0,50
A33: Lucro por unidade no preço sugerido | D33: =D32*(1-'Custos do mês'!B17)-D29
A34: Preço sugerido no aplicativo de delivery | D34: =IF('Custos do mês'!B18=0,"",IFERROR(ROUNDUP(D29/(1-'Custos do mês'!B18-'Custos do mês'!B17-'Custos do mês'!B19)*2,0)/2,0))
A36: Preço que você cobra hoje (opcional)
A37: Quanto sobra por unidade no preço de hoje | D37: =IF(B36="","",B36*(1-'Custos do mês'!B17)-D29) | E37: se der negativo, o preço de hoje não cobre o custo real

Sheet Ficha 2
A1: Ficha 2 · ficha de preço
A2: Produto
A3: Rendimento da receita (unidades)
A4: Tempo para fazer a receita inteira (min)
A5: Embalagem por unidade vendida | E5: forminha, caixa, pote, etiqueta: some o que vai em cada unidade
A7: Ingrediente | B7: Qtd usada | C7: Unidade | D7: Custo
C8: =IF(A8="","",IFERROR(INDEX(Insumos!$B$5:$B$104,MATCH(A8,Insumos!$A$5:$A$104,0)),"")) | D8: =IF(OR(A8="",B8=""),"",IFERROR(B8*INDEX(Insumos!$E$5:$E$104,MATCH(A8,Insumos!$A$5:$A$104,0)),"preencha o preço"))
C9: =IF(A9="","",IFERROR(INDEX(Insumos!$B$5:$B$104,MATCH(A9,Insumos!$A$5:$A$104,0)),"")) | D9: =IF(OR(A9="",B9=""),"",IFERROR(B9*INDEX(Insumos!$E$5:$E$104,MATCH(A9,Insumos!$A$5:$A$104,0)),"preencha o preço"))
C10: =IF(A10="","",IFERROR(INDEX(Insumos!$B$5:$B$104,MATCH(A10,Insumos!$A$5:$A$104,0)),"")) | D10: =IF(OR(A10="",B10=""),"",IFERROR(B10*INDEX(Insumos!$E$5:$E$104,MATCH(A10,Insumos!$A$5:$A$104,0)),"preencha o preço"))
C11: =IF(A11="","",IFERROR(INDEX(Insumos!$B$5:$B$104,MATCH(A11,Insumos!$A$5:$A$104,0)),"")) | D11: =IF(OR(A11="",B11=""),"",IFERROR(B11*INDEX(Insumos!$E$5:$E$104,MATCH(A11,Insumos!$A$5:$A$104,0)),"preencha o preço"))
C12: =IF(A12="","",IFERROR(INDEX(Insumos!$B$5:$B$104,MATCH(A12,Insumos!$A$5:$A$104,0)),"")) | D12: =IF(OR(A12="",B12=""),"",IFERROR(B12*INDEX(Insumos!$E$5:$E$104,MATCH(A12,Insumos!$A$5:$A$104,0)),"preencha o preço"))
C13: =IF(A13="","",IFERROR(INDEX(Insumos!$B$5:$B$104,MATCH(A13,Insumos!$A$5:$A$104,0)),"")) | D13: =IF(OR(A13="",B13=""),"",IFERROR(B13*INDEX(Insumos!$E$5:$E$104,MATCH(A13,Insumos!$A$5:$A$104,0)),"preencha o preço"))
C14: =IF(A14="","",IFERROR(INDEX(Insumos!$B$5:$B$104,MATCH(A14,Insumos!$A$5:$A$104,0)),"")) | D14: =IF(OR(A14="",B14=""),"",IFERROR(B14*INDEX(Insumos!$E$5:$E$104,MATCH(A14,Insumos!$A$5:$A$104,0)),"preencha o preço"))
C15: =IF(A15="","",IFERROR(INDEX(Insumos!$B$5:$B$104,MATCH(A15,Insumos!$A$5:$A$104,0)),"")) | D15: =IF(OR(A15="",B15=""),"",IFERROR(B15*INDEX(Insumos!$E$5:$E$104,MATCH(A15,Insumos!$A$5:$A$104,0)),"preencha o preço"))
C16: =IF(A16="","",IFERROR(INDEX(Insumos!$B$5:$B$104,MATCH(A16,Insumos!$A$5:$A$104,0)),"")) | D16: =IF(OR(A16="",B16=""),"",IFERROR(B16*INDEX(Insumos!$E$5:$E$104,MATCH(A16,Insumos!$A$5:$A$104,0)),"preencha o preço"))
C17: =IF(A17="","",IFERROR(INDEX(Insumos!$B$5:$B$104,MATCH(A17,Insumos!$A$5:$A$104,0)),"")) | D17: =IF(OR(A17="",B17=""),"",IFERROR(B17*INDEX(Insumos!$E$5:$E$104,MATCH(A17,Insumos!$A$5:$A$104,0)),"preencha o preço"))
C18: =IF(A18="","",IFERROR(INDEX(Insumos!$B$5:$B$104,MATCH(A18,Insumos!$A$5:$A$104,0)),"")) | D18: =IF(OR(A18="",B18=""),"",IFERROR(B18*INDEX(Insumos!$E$5:$E$104,MATCH(A18,Insumos!$A$5:$A$104,0)),"preencha o preço"))
C19: =IF(A19="","",IFERROR(INDEX(Insumos!$B$5:$B$104,MATCH(A19,Insumos!$A$5:$A$104,0)),"")) | D19: =IF(OR(A19="",B19=""),"",IFERROR(B19*INDEX(Insumos!$E$5:$E$104,MATCH(A19,Insumos!$A$5:$A$104,0)),"preencha o preço"))
... C22: =IF(A22="","",IFERROR(INDEX(Insumos!$B$5:$B$104,MATCH(A22,Insumos!$A$5:$A$104,0)),"")) | D22: =IF(OR(A22="",B22=""),"",IFERROR(B22*INDEX(Insumos!$E$5:$E$104,MATCH(A22,Insumos!$A$5:$A$104,0)),"preencha o preço"))
A23: Ingredientes da receita | D23: =SUM(D8:D22)
A25: Ingredientes por unidade | D25: =IFERROR(D23/B3,0)
A26: Embalagem por unidade | D26: =N(B5)
A27: Seu trabalho por unidade | D27: =IFERROR(B4/60*'Custos do mês'!B5/B3,0)
A28: Gastos fixos por unidade | D28: =IFERROR(B4/60*'Custos do mês'!B15/B3,0)
A29: CUSTO REAL POR UNIDADE | D29: =SUM(D25:D28)
A31: Preço mínimo (sem lucro, já com a taxa) | D31: =IFERROR(ROUNDUP(D29/(1-'Custos do mês'!B17)*2,0)/2,0) | E31: abaixo disso você paga para trabalhar
A32: PREÇO SUGERIDO (encomenda) | D32: =IFERROR(ROUNDUP(D29/(1-'Custos do mês'!B17-'Custos do mês'!B19)*2,0)/2,0) | E32: arredondado para cima em R$ 0,50
A33: Lucro por unidade no preço sugerido | D33: =D32*(1-'Custos do mês'!B17)-D29
A34: Preço sugerido no aplicativo de delivery | D34: =IF('Custos do mês'!B18=0,"",IFERROR(ROUNDUP(D29/(1-'Custos do mês'!B18-'Custos do mês'!B17-'Custos do mês'!B19)*2,0)/2,0))
A36: Preço que você cobra hoje (opcional)
A37: Quanto sobra por unidade no preço de hoje | D37: =IF(B36="","",B36*(1-'Custos do mês'!B17)-D29) | E37: se der negativo, o preço de hoje não cobre o custo real

Sheet Ficha 3
A1: Ficha 3 · ficha de preço
A2: Produto
A3: Rendimento da receita (unidades)
A4: Tempo para fazer a receita inteira (min)
A5: Embalagem por unidade vendida | E5: forminha, caixa, pote, etiqueta: some o que vai em cada unidade
A7: Ingrediente | B7: Qtd usada | C7: Unidade | D7: Custo
C8: =IF(A8="","",IFERROR(INDEX(Insumos!$B$5:$B$104,MATCH(A8,Insumos!$A$5:$A$104,0)),"")) | D8: =IF(OR(A8="",B8=""),"",IFERROR(B8*INDEX(Insumos!$E$5:$E$104,MATCH(A8,Insumos!$A$5:$A$104,0)),"preencha o preço"))
C9: =IF(A9="","",IFERROR(INDEX(Insumos!$B$5:$B$104,MATCH(A9,Insumos!$A$5:$A$104,0)),"")) | D9: =IF(OR(A9="",B9=""),"",IFERROR(B9*INDEX(Insumos!$E$5:$E$104,MATCH(A9,Insumos!$A$5:$A$104,0)),"preencha o preço"))
C10: =IF(A10="","",IFERROR(INDEX(Insumos!$B$5:$B$104,MATCH(A10,Insumos!$A$5:$A$104,0)),"")) | D10: =IF(OR(A10="",B10=""),"",IFERROR(B10*INDEX(Insumos!$E$5:$E$104,MATCH(A10,Insumos!$A$5:$A$104,0)),"preencha o preço"))
C11: =IF(A11="","",IFERROR(INDEX(Insumos!$B$5:$B$104,MATCH(A11,Insumos!$A$5:$A$104,0)),"")) | D11: =IF(OR(A11="",B11=""),"",IFERROR(B11*INDEX(Insumos!$E$5:$E$104,MATCH(A11,Insumos!$A$5:$A$104,0)),"preencha o preço"))
C12: =IF(A12="","",IFERROR(INDEX(Insumos!$B$5:$B$104,MATCH(A12,Insumos!$A$5:$A$104,0)),"")) | D12: =IF(OR(A12="",B12=""),"",IFERROR(B12*INDEX(Insumos!$E$5:$E$104,MATCH(A12,Insumos!$A$5:$A$104,0)),"preencha o preço"))
C13: =IF(A13="","",IFERROR(INDEX(Insumos!$B$5:$B$104,MATCH(A13,Insumos!$A$5:$A$104,0)),"")) | D13: =IF(OR(A13="",B13=""),"",IFERROR(B13*INDEX(Insumos!$E$5:$E$104,MATCH(A13,Insumos!$A$5:$A$104,0)),"preencha o preço"))
C14: =IF(A14="","",IFERROR(INDEX(Insumos!$B$5:$B$104,MATCH(A14,Insumos!$A$5:$A$104,0)),"")) | D14: =IF(OR(A14="",B14=""),"",IFERROR(B14*INDEX(Insumos!$E$5:$E$104,MATCH(A14,Insumos!$A$5:$A$104,0)),"preencha o preço"))
C15: =IF(A15="","",IFERROR(INDEX(Insumos!$B$5:$B$104,MATCH(A15,Insumos!$A$5:$A$104,0)),"")) | D15: =IF(OR(A15="",B15=""),"",IFERROR(B15*INDEX(Insumos!$E$5:$E$104,MATCH(A15,Insumos!$A$5:$A$104,0)),"preencha o preço"))
C16: =IF(A16="","",IFERROR(INDEX(Insumos!$B$5:$B$104,MATCH(A16,Insumos!$A$5:$A$104,0)),"")) | D16: =IF(OR(A16="",B16=""),"",IFERROR(B16*INDEX(Insumos!$E$5:$E$104,MATCH(A16,Insumos!$A$5:$A$104,0)),"preencha o preço"))
C17: =IF(A17="","",IFERROR(INDEX(Insumos!$B$5:$B$104,MATCH(A17,Insumos!$A$5:$A$104,0)),"")) | D17: =IF(OR(A17="",B17=""),"",IFERROR(B17*INDEX(Insumos!$E$5:$E$104,MATCH(A17,Insumos!$A$5:$A$104,0)),"preencha o preço"))
C18: =IF(A18="","",IFERROR(INDEX(Insumos!$B$5:$B$104,MATCH(A18,Insumos!$A$5:$A$104,0)),"")) | D18: =IF(OR(A18="",B18=""),"",IFERROR(B18*INDEX(Insumos!$E$5:$E$104,MATCH(A18,Insumos!$A$5:$A$104,0)),"preencha o preço"))
C19: =IF(A19="","",IFERROR(INDEX(Insumos!$B$5:$B$104,MATCH(A19,Insumos!$A$5:$A$104,0)),"")) | D19: =IF(OR(A19="",B19=""),"",IFERROR(B19*INDEX(Insumos!$E$5:$E$104,MATCH(A19,Insumos!$A$5:$A$104,0)),"preencha o preço"))
... C22: =IF(A22="","",IFERROR(INDEX(Insumos!$B$5:$B$104,MATCH(A22,Insumos!$A$5:$A$104,0)),"")) | D22: =IF(OR(A22="",B22=""),"",IFERROR(B22*INDEX(Insumos!$E$5:$E$104,MATCH(A22,Insumos!$A$5:$A$104,0)),"preencha o preço"))
A23: Ingredientes da receita | D23: =SUM(D8:D22)
A25: Ingredientes por unidade | D25: =IFERROR(D23/B3,0)
A26: Embalagem por unidade | D26: =N(B5)
A27: Seu trabalho por unidade | D27: =IFERROR(B4/60*'Custos do mês'!B5/B3,0)
A28: Gastos fixos por unidade | D28: =IFERROR(B4/60*'Custos do mês'!B15/B3,0)
A29: CUSTO REAL POR UNIDADE | D29: =SUM(D25:D28)
A31: Preço mínimo (sem lucro, já com a taxa) | D31: =IFERROR(ROUNDUP(D29/(1-'Custos do mês'!B17)*2,0)/2,0) | E31: abaixo disso você paga para trabalhar
A32: PREÇO SUGERIDO (encomenda) | D32: =IFERROR(ROUNDUP(D29/(1-'Custos do mês'!B17-'Custos do mês'!B19)*2,0)/2,0) | E32: arredondado para cima em R$ 0,50
A33: Lucro por unidade no preço sugerido | D33: =D32*(1-'Custos do mês'!B17)-D29
A34: Preço sugerido no aplicativo de delivery | D34: =IF('Custos do mês'!B18=0,"",IFERROR(ROUNDUP(D29/(1-'Custos do mês'!B18-'Custos do mês'!B17-'Custos do mês'!B19)*2,0)/2,0))
A36: Preço que você cobra hoje (opcional)
A37: Quanto sobra por unidade no preço de hoje | D37: =IF(B36="","",B36*(1-'Custos do mês'!B17)-D29) | E37: se der negativo, o preço de hoje não cobre o custo real

Sheet Ficha 4
A1: Ficha 4 · ficha de preço
A2: Produto
A3: Rendimento da receita (unidades)
A4: Tempo para fazer a receita inteira (min)
A5: Embalagem por unidade vendida | E5: forminha, caixa, pote, etiqueta: some o que vai em cada unidade
A7: Ingrediente | B7: Qtd usada | C7: Unidade | D7: Custo
C8: =IF(A8="","",IFERROR(INDEX(Insumos!$B$5:$B$104,MATCH(A8,Insumos!$A$5:$A$104,0)),"")) | D8: =IF(OR(A8="",B8=""),"",IFERROR(B8*INDEX(Insumos!$E$5:$E$104,MATCH(A8,Insumos!$A$5:$A$104,0)),"preencha o preço"))
C9: =IF(A9="","",IFERROR(INDEX(Insumos!$B$5:$B$104,MATCH(A9,Insumos!$A$5:$A$104,0)),"")) | D9: =IF(OR(A9="",B9=""),"",IFERROR(B9*INDEX(Insumos!$E$5:$E$104,MATCH(A9,Insumos!$A$5:$A$104,0)),"preencha o preço"))
C10: =IF(A10="","",IFERROR(INDEX(Insumos!$B$5:$B$104,MATCH(A10,Insumos!$A$5:$A$104,0)),"")) | D10: =IF(OR(A10="",B10=""),"",IFERROR(B10*INDEX(Insumos!$E$5:$E$104,MATCH(A10,Insumos!$A$5:$A$104,0)),"preencha o preço"))
C11: =IF(A11="","",IFERROR(INDEX(Insumos!$B$5:$B$104,MATCH(A11,Insumos!$A$5:$A$104,0)),"")) | D11: =IF(OR(A11="",B11=""),"",IFERROR(B11*INDEX(Insumos!$E$5:$E$104,MATCH(A11,Insumos!$A$5:$A$104,0)),"preencha o preço"))
C12: =IF(A12="","",IFERROR(INDEX(Insumos!$B$5:$B$104,MATCH(A12,Insumos!$A$5:$A$104,0)),"")) | D12: =IF(OR(A12="",B12=""),"",IFERROR(B12*INDEX(Insumos!$E$5:$E$104,MATCH(A12,Insumos!$A$5:$A$104,0)),"preencha o preço"))
C13: =IF(A13="","",IFERROR(INDEX(Insumos!$B$5:$B$104,MATCH(A13,Insumos!$A$5:$A$104,0)),"")) | D13: =IF(OR(A13="",B13=""),"",IFERROR(B13*INDEX(Insumos!$E$5:$E$104,MATCH(A13,Insumos!$A$5:$A$104,0)),"preencha o preço"))
C14: =IF(A14="","",IFERROR(INDEX(Insumos!$B$5:$B$104,MATCH(A14,Insumos!$A$5:$A$104,0)),"")) | D14: =IF(OR(A14="",B14=""),"",IFERROR(B14*INDEX(Insumos!$E$5:$E$104,MATCH(A14,Insumos!$A$5:$A$104,0)),"preencha o preço"))
C15: =IF(A15="","",IFERROR(INDEX(Insumos!$B$5:$B$104,MATCH(A15,Insumos!$A$5:$A$104,0)),"")) | D15: =IF(OR(A15="",B15=""),"",IFERROR(B15*INDEX(Insumos!$E$5:$E$104,MATCH(A15,Insumos!$A$5:$A$104,0)),"preencha o preço"))
C16: =IF(A16="","",IFERROR(INDEX(Insumos!$B$5:$B$104,MATCH(A16,Insumos!$A$5:$A$104,0)),"")) | D16: =IF(OR(A16="",B16=""),"",IFERROR(B16*INDEX(Insumos!$E$5:$E$104,MATCH(A16,Insumos!$A$5:$A$104,0)),"preencha o preço"))
C17: =IF(A17="","",IFERROR(INDEX(Insumos!$B$5:$B$104,MATCH(A17,Insumos!$A$5:$A$104,0)),"")) | D17: =IF(OR(A17="",B17=""),"",IFERROR(B17*INDEX(Insumos!$E$5:$E$104,MATCH(A17,Insumos!$A$5:$A$104,0)),"preencha o preço"))
C18: =IF(A18="","",IFERROR(INDEX(Insumos!$B$5:$B$104,MATCH(A18,Insumos!$A$5:$A$104,0)),"")) | D18: =IF(OR(A18="",B18=""),"",IFERROR(B18*INDEX(Insumos!$E$5:$E$104,MATCH(A18,Insumos!$A$5:$A$104,0)),"preencha o preço"))
C19: =IF(A19="","",IFERROR(INDEX(Insumos!$B$5:$B$104,MATCH(A19,Insumos!$A$5:$A$104,0)),"")) | D19: =IF(OR(A19="",B19=""),"",IFERROR(B19*INDEX(Insumos!$E$5:$E$104,MATCH(A19,Insumos!$A$5:$A$104,0)),"preencha o preço"))
... C22: =IF(A22="","",IFERROR(INDEX(Insumos!$B$5:$B$104,MATCH(A22,Insumos!$A$5:$A$104,0)),"")) | D22: =IF(OR(A22="",B22=""),"",IFERROR(B22*INDEX(Insumos!$E$5:$E$104,MATCH(A22,Insumos!$A$5:$A$104,0)),"preencha o preço"))
A23: Ingredientes da receita | D23: =SUM(D8:D22)
A25: Ingredientes por unidade | D25: =IFERROR(D23/B3,0)
A26: Embalagem por unidade | D26: =N(B5)
A27: Seu trabalho por unidade | D27: =IFERROR(B4/60*'Custos do mês'!B5/B3,0)
A28: Gastos fixos por unidade | D28: =IFERROR(B4/60*'Custos do mês'!B15/B3,0)
A29: CUSTO REAL POR UNIDADE | D29: =SUM(D25:D28)
A31: Preço mínimo (sem lucro, já com a taxa) | D31: =IFERROR(ROUNDUP(D29/(1-'Custos do mês'!B17)*2,0)/2,0) | E31: abaixo disso você paga para trabalhar
A32: PREÇO SUGERIDO (encomenda) | D32: =IFERROR(ROUNDUP(D29/(1-'Custos do mês'!B17-'Custos do mês'!B19)*2,0)/2,0) | E32: arredondado para cima em R$ 0,50
A33: Lucro por unidade no preço sugerido | D33: =D32*(1-'Custos do mês'!B17)-D29
A34: Preço sugerido no aplicativo de delivery | D34: =IF('Custos do mês'!B18=0,"",IFERROR(ROUNDUP(D29/(1-'Custos do mês'!B18-'Custos do mês'!B17-'Custos do mês'!B19)*2,0)/2,0))
A36: Preço que você cobra hoje (opcional)
A37: Quanto sobra por unidade no preço de hoje | D37: =IF(B36="","",B36*(1-'Custos do mês'!B17)-D29) | E37: se der negativo, o preço de hoje não cobre o custo real

Sheet Ficha 5
A1: Ficha 5 · ficha de preço
A2: Produto
A3: Rendimento da receita (unidades)
A4: Tempo para fazer a receita inteira (min)
A5: Embalagem por unidade vendida | E5: forminha, caixa, pote, etiqueta: some o que vai em cada unidade
A7: Ingrediente | B7: Qtd usada | C7: Unidade | D7: Custo
C8: =IF(A8="","",IFERROR(INDEX(Insumos!$B$5:$B$104,MATCH(A8,Insumos!$A$5:$A$104,0)),"")) | D8: =IF(OR(A8="",B8=""),"",IFERROR(B8*INDEX(Insumos!$E$5:$E$104,MATCH(A8,Insumos!$A$5:$A$104,0)),"preencha o preço"))
C9: =IF(A9="","",IFERROR(INDEX(Insumos!$B$5:$B$104,MATCH(A9,Insumos!$A$5:$A$104,0)),"")) | D9: =IF(OR(A9="",B9=""),"",IFERROR(B9*INDEX(Insumos!$E$5:$E$104,MATCH(A9,Insumos!$A$5:$A$104,0)),"preencha o preço"))
C10: =IF(A10="","",IFERROR(INDEX(Insumos!$B$5:$B$104,MATCH(A10,Insumos!$A$5:$A$104,0)),"")) | D10: =IF(OR(A10="",B10=""),"",IFERROR(B10*INDEX(Insumos!$E$5:$E$104,MATCH(A10,Insumos!$A$5:$A$104,0)),"preencha o preço"))
C11: =IF(A11="","",IFERROR(INDEX(Insumos!$B$5:$B$104,MATCH(A11,Insumos!$A$5:$A$104,0)),"")) | D11: =IF(OR(A11="",B11=""),"",IFERROR(B11*INDEX(Insumos!$E$5:$E$104,MATCH(A11,Insumos!$A$5:$A$104,0)),"preencha o preço"))
C12: =IF(A12="","",IFERROR(INDEX(Insumos!$B$5:$B$104,MATCH(A12,Insumos!$A$5:$A$104,0)),"")) | D12: =IF(OR(A12="",B12=""),"",IFERROR(B12*INDEX(Insumos!$E$5:$E$104,MATCH(A12,Insumos!$A$5:$A$104,0)),"preencha o preço"))
C13: =IF(A13="","",IFERROR(INDEX(Insumos!$B$5:$B$104,MATCH(A13,Insumos!$A$5:$A$104,0)),"")) | D13: =IF(OR(A13="",B13=""),"",IFERROR(B13*INDEX(Insumos!$E$5:$E$104,MATCH(A13,Insumos!$A$5:$A$104,0)),"preencha o preço"))
C14: =IF(A14="","",IFERROR(INDEX(Insumos!$B$5:$B$104,MATCH(A14,Insumos!$A$5:$A$104,0)),"")) | D14: =IF(OR(A14="",B14=""),"",IFERROR(B14*INDEX(Insumos!$E$5:$E$104,MATCH(A14,Insumos!$A$5:$A$104,0)),"preencha o preço"))
C15: =IF(A15="","",IFERROR(INDEX(Insumos!$B$5:$B$104,MATCH(A15,Insumos!$A$5:$A$104,0)),"")) | D15: =IF(OR(A15="",B15=""),"",IFERROR(B15*INDEX(Insumos!$E$5:$E$104,MATCH(A15,Insumos!$A$5:$A$104,0)),"preencha o preço"))
C16: =IF(A16="","",IFERROR(INDEX(Insumos!$B$5:$B$104,MATCH(A16,Insumos!$A$5:$A$104,0)),"")) | D16: =IF(OR(A16="",B16=""),"",IFERROR(B16*INDEX(Insumos!$E$5:$E$104,MATCH(A16,Insumos!$A$5:$A$104,0)),"preencha o preço"))
C17: =IF(A17="","",IFERROR(INDEX(Insumos!$B$5:$B$104,MATCH(A17,Insumos!$A$5:$A$104,0)),"")) | D17: =IF(OR(A17="",B17=""),"",IFERROR(B17*INDEX(Insumos!$E$5:$E$104,MATCH(A17,Insumos!$A$5:$A$104,0)),"preencha o preço"))
C18: =IF(A18="","",IFERROR(INDEX(Insumos!$B$5:$B$104,MATCH(A18,Insumos!$A$5:$A$104,0)),"")) | D18: =IF(OR(A18="",B18=""),"",IFERROR(B18*INDEX(Insumos!$E$5:$E$104,MATCH(A18,Insumos!$A$5:$A$104,0)),"preencha o preço"))
C19: =IF(A19="","",IFERROR(INDEX(Insumos!$B$5:$B$104,MATCH(A19,Insumos!$A$5:$A$104,0)),"")) | D19: =IF(OR(A19="",B19=""),"",IFERROR(B19*INDEX(Insumos!$E$5:$E$104,MATCH(A19,Insumos!$A$5:$A$104,0)),"preencha o preço"))
... C22: =IF(A22="","",IFERROR(INDEX(Insumos!$B$5:$B$104,MATCH(A22,Insumos!$A$5:$A$104,0)),"")) | D22: =IF(OR(A22="",B22=""),"",IFERROR(B22*INDEX(Insumos!$E$5:$E$104,MATCH(A22,Insumos!$A$5:$A$104,0)),"preencha o preço"))
A23: Ingredientes da receita | D23: =SUM(D8:D22)
A25: Ingredientes por unidade | D25: =IFERROR(D23/B3,0)
A26: Embalagem por unidade | D26: =N(B5)
A27: Seu trabalho por unidade | D27: =IFERROR(B4/60*'Custos do mês'!B5/B3,0)
A28: Gastos fixos por unidade | D28: =IFERROR(B4/60*'Custos do mês'!B15/B3,0)
A29: CUSTO REAL POR UNIDADE | D29: =SUM(D25:D28)
A31: Preço mínimo (sem lucro, já com a taxa) | D31: =IFERROR(ROUNDUP(D29/(1-'Custos do mês'!B17)*2,0)/2,0) | E31: abaixo disso você paga para trabalhar
A32: PREÇO SUGERIDO (encomenda) | D32: =IFERROR(ROUNDUP(D29/(1-'Custos do mês'!B17-'Custos do mês'!B19)*2,0)/2,0) | E32: arredondado para cima em R$ 0,50
A33: Lucro por unidade no preço sugerido | D33: =D32*(1-'Custos do mês'!B17)-D29
A34: Preço sugerido no aplicativo de delivery | D34: =IF('Custos do mês'!B18=0,"",IFERROR(ROUNDUP(D29/(1-'Custos do mês'!B18-'Custos do mês'!B17-'Custos do mês'!B19)*2,0)/2,0))
A36: Preço que você cobra hoje (opcional)
A37: Quanto sobra por unidade no preço de hoje | D37: =IF(B36="","",B36*(1-'Custos do mês'!B17)-D29) | E37: se der negativo, o preço de hoje não cobre o custo real

Sheet Ficha 6
A1: Ficha 6 · ficha de preço
A2: Produto
A3: Rendimento da receita (unidades)
A4: Tempo para fazer a receita inteira (min)
A5: Embalagem por unidade vendida | E5: forminha, caixa, pote, etiqueta: some o que vai em cada unidade
A7: Ingrediente | B7: Qtd usada | C7: Unidade | D7: Custo
C8: =IF(A8="","",IFERROR(INDEX(Insumos!$B$5:$B$104,MATCH(A8,Insumos!$A$5:$A$104,0)),"")) | D8: =IF(OR(A8="",B8=""),"",IFERROR(B8*INDEX(Insumos!$E$5:$E$104,MATCH(A8,Insumos!$A$5:$A$104,0)),"preencha o preço"))
C9: =IF(A9="","",IFERROR(INDEX(Insumos!$B$5:$B$104,MATCH(A9,Insumos!$A$5:$A$104,0)),"")) | D9: =IF(OR(A9="",B9=""),"",IFERROR(B9*INDEX(Insumos!$E$5:$E$104,MATCH(A9,Insumos!$A$5:$A$104,0)),"preencha o preço"))
C10: =IF(A10="","",IFERROR(INDEX(Insumos!$B$5:$B$104,MATCH(A10,Insumos!$A$5:$A$104,0)),"")) | D10: =IF(OR(A10="",B10=""),"",IFERROR(B10*INDEX(Insumos!$E$5:$E$104,MATCH(A10,Insumos!$A$5:$A$104,0)),"preencha o preço"))
C11: =IF(A11="","",IFERROR(INDEX(Insumos!$B$5:$B$104,MATCH(A11,Insumos!$A$5:$A$104,0)),"")) | D11: =IF(OR(A11="",B11=""),"",IFERROR(B11*INDEX(Insumos!$E$5:$E$104,MATCH(A11,Insumos!$A$5:$A$104,0)),"preencha o preço"))
C12: =IF(A12="","",IFERROR(INDEX(Insumos!$B$5:$B$104,MATCH(A12,Insumos!$A$5:$A$104,0)),"")) | D12: =IF(OR(A12="",B12=""),"",IFERROR(B12*INDEX(Insumos!$E$5:$E$104,MATCH(A12,Insumos!$A$5:$A$104,0)),"preencha o preço"))
C13: =IF(A13="","",IFERROR(INDEX(Insumos!$B$5:$B$104,MATCH(A13,Insumos!$A$5:$A$104,0)),"")) | D13: =IF(OR(A13="",B13=""),"",IFERROR(B13*INDEX(Insumos!$E$5:$E$104,MATCH(A13,Insumos!$A$5:$A$104,0)),"preencha o preço"))
C14: =IF(A14="","",IFERROR(INDEX(Insumos!$B$5:$B$104,MATCH(A14,Insumos!$A$5:$A$104,0)),"")) | D14: =IF(OR(A14="",B14=""),"",IFERROR(B14*INDEX(Insumos!$E$5:$E$104,MATCH(A14,Insumos!$A$5:$A$104,0)),"preencha o preço"))
C15: =IF(A15="","",IFERROR(INDEX(Insumos!$B$5:$B$104,MATCH(A15,Insumos!$A$5:$A$104,0)),"")) | D15: =IF(OR(A15="",B15=""),"",IFERROR(B15*INDEX(Insumos!$E$5:$E$104,MATCH(A15,Insumos!$A$5:$A$104,0)),"preencha o preço"))
C16: =IF(A16="","",IFERROR(INDEX(Insumos!$B$5:$B$104,MATCH(A16,Insumos!$A$5:$A$104,0)),"")) | D16: =IF(OR(A16="",B16=""),"",IFERROR(B16*INDEX(Insumos!$E$5:$E$104,MATCH(A16,Insumos!$A$5:$A$104,0)),"preencha o preço"))
C17: =IF(A17="","",IFERROR(INDEX(Insumos!$B$5:$B$104,MATCH(A17,Insumos!$A$5:$A$104,0)),"")) | D17: =IF(OR(A17="",B17=""),"",IFERROR(B17*INDEX(Insumos!$E$5:$E$104,MATCH(A17,Insumos!$A$5:$A$104,0)),"preencha o preço"))
C18: =IF(A18="","",IFERROR(INDEX(Insumos!$B$5:$B$104,MATCH(A18,Insumos!$A$5:$A$104,0)),"")) | D18: =IF(OR(A18="",B18=""),"",IFERROR(B18*INDEX(Insumos!$E$5:$E$104,MATCH(A18,Insumos!$A$5:$A$104,0)),"preencha o preço"))
C19: =IF(A19="","",IFERROR(INDEX(Insumos!$B$5:$B$104,MATCH(A19,Insumos!$A$5:$A$104,0)),"")) | D19: =IF(OR(A19="",B19=""),"",IFERROR(B19*INDEX(Insumos!$E$5:$E$104,MATCH(A19,Insumos!$A$5:$A$104,0)),"preencha o preço"))
... C22: =IF(A22="","",IFERROR(INDEX(Insumos!$B$5:$B$104,MATCH(A22,Insumos!$A$5:$A$104,0)),"")) | D22: =IF(OR(A22="",B22=""),"",IFERROR(B22*INDEX(Insumos!$E$5:$E$104,MATCH(A22,Insumos!$A$5:$A$104,0)),"preencha o preço"))
A23: Ingredientes da receita | D23: =SUM(D8:D22)
A25: Ingredientes por unidade | D25: =IFERROR(D23/B3,0)
A26: Embalagem por unidade | D26: =N(B5)
A27: Seu trabalho por unidade | D27: =IFERROR(B4/60*'Custos do mês'!B5/B3,0)
A28: Gastos fixos por unidade | D28: =IFERROR(B4/60*'Custos do mês'!B15/B3,0)
A29: CUSTO REAL POR UNIDADE | D29: =SUM(D25:D28)
A31: Preço mínimo (sem lucro, já com a taxa) | D31: =IFERROR(ROUNDUP(D29/(1-'Custos do mês'!B17)*2,0)/2,0) | E31: abaixo disso você paga para trabalhar
A32: PREÇO SUGERIDO (encomenda) | D32: =IFERROR(ROUNDUP(D29/(1-'Custos do mês'!B17-'Custos do mês'!B19)*2,0)/2,0) | E32: arredondado para cima em R$ 0,50
A33: Lucro por unidade no preço sugerido | D33: =D32*(1-'Custos do mês'!B17)-D29
A34: Preço sugerido no aplicativo de delivery | D34: =IF('Custos do mês'!B18=0,"",IFERROR(ROUNDUP(D29/(1-'Custos do mês'!B18-'Custos do mês'!B17-'Custos do mês'!B19)*2,0)/2,0))
A36: Preço que você cobra hoje (opcional)
A37: Quanto sobra por unidade no preço de hoje | D37: =IF(B36="","",B36*(1-'Custos do mês'!B17)-D29) | E37: se der negativo, o preço de hoje não cobre o custo real

Sheet Tabela WhatsApp
A1: Tabela de preços para copiar
A2: Copie a coluna D e cole no WhatsApp ou no seu cardápio.
A4: Produto | B4: Encomenda | C4: App | D4: Linha pronta
A5: =IF('Ficha 1'!B2="","",'Ficha 1'!B2) | B5: =IF('Ficha 1'!B2="","",'Ficha 1'!D32) | C5: =IF(OR('Ficha 1'!B2="",'Ficha 1'!D34=""),"",'Ficha 1'!D34) | D5: =IF('Ficha 1'!B2="","",'Ficha 1'!B2&": R$ "&FIXED('Ficha 1'!D32,2))
A6: =IF('Ficha 2'!B2="","",'Ficha 2'!B2) | B6: =IF('Ficha 2'!B2="","",'Ficha 2'!D32) | C6: =IF(OR('Ficha 2'!B2="",'Ficha 2'!D34=""),"",'Ficha 2'!D34) | D6: =IF('Ficha 2'!B2="","",'Ficha 2'!B2&": R$ "&FIXED('Ficha 2'!D32,2))
A7: =IF('Ficha 3'!B2="","",'Ficha 3'!B2) | B7: =IF('Ficha 3'!B2="","",'Ficha 3'!D32) | C7: =IF(OR('Ficha 3'!B2="",'Ficha 3'!D34=""),"",'Ficha 3'!D34) | D7: =IF('Ficha 3'!B2="","",'Ficha 3'!B2&": R$ "&FIXED('Ficha 3'!D32,2))
A8: =IF('Ficha 4'!B2="","",'Ficha 4'!B2) | B8: =IF('Ficha 4'!B2="","",'Ficha 4'!D32) | C8: =IF(OR('Ficha 4'!B2="",'Ficha 4'!D34=""),"",'Ficha 4'!D34) | D8: =IF('Ficha 4'!B2="","",'Ficha 4'!B2&": R$ "&FIXED('Ficha 4'!D32,2))
A9: =IF('Ficha 5'!B2="","",'Ficha 5'!B2) | B9: =IF('Ficha 5'!B2="","",'Ficha 5'!D32) | C9: =IF(OR('Ficha 5'!B2="",'Ficha 5'!D34=""),"",'Ficha 5'!D34) | D9: =IF('Ficha 5'!B2="","",'Ficha 5'!B2&": R$ "&FIXED('Ficha 5'!D32,2))
A10: =IF('Ficha 6'!B2="","",'Ficha 6'!B2) | B10: =IF('Ficha 6'!B2="","",'Ficha 6'!D32) | C10: =IF(OR('Ficha 6'!B2="",'Ficha 6'!D34=""),"",'Ficha 6'!D34) | D10: =IF('Ficha 6'!B2="","",'Ficha 6'!B2&": R$ "&FIXED('Ficha 6'!D32,2))

Sheet Exemplo
A1: Exemplo: brigadeiro tradicional
A2: VALORES DE EXEMPLO para mostrar o cálculo. Não são preços de mercado nem da sua região.
A4: Ingrediente | B4: Qtd embalagem | C4: Preço exemplo | D4: Qtd usada | E4: Custo
A5: Leite condensado (g) | B5: 395 | C5: 7 | D5: 790 | E5: =C5/B5*D5
A6: Manteiga (g) | B6: 200 | C6: 9 | D6: 20 | E6: =C6/B6*D6
A7: Chocolate em pó 50% (g) | B7: 200 | C7: 8 | D7: 40 | E7: =C7/B7*D7
A8: Granulado (g) | B8: 500 | C8: 12 | D8: 120 | E8: =C8/B8*D8
A9: Forminha nº 4 (un) | B9: 100 | C9: 6 | D9: 50 | E9: =C9/B9*D9
A11: Rendimento (unidades) | B11: 50
A12: Tempo da receita (min) | B12: 90
A13: Valor da hora (exemplo) | B13: 16.67
A14: Gasto fixo por hora (exemplo) | B14: 3
A15: Taxa do pagamento (exemplo) | B15: 0.04
A16: Margem desejada (exemplo) | B16: 0.3
A18: Ingredientes e forminha por unidade | B18: =SUM(E5:E9)/B11
A19: Trabalho por unidade | B19: =B12/60*B13/B11
A20: Gastos fixos por unidade | B20: =B12/60*B14/B11
A21: CUSTO REAL POR UNIDADE | B21: =SUM(B18:B20)
A22: Preço mínimo | B22: =ROUNDUP(B21/(1-B15)*2,0)/2
A23: PREÇO SUGERIDO | B23: =ROUNDUP(B21/(1-B15-B16)*2,0)/2
A24: Lucro por unidade | B24: =B23*(1-B15)-B21
A26: Repare: sem contar o trabalho e os gastos fixos, o custo parece bem menor do que é.
